etc_jupyterlab_telemetry_coursera/__init__.py
etc_jupyterlab_telemetry_coursera/_version.py
etc_jupyterlab_telemetry_coursera/application.py
etc_jupyterlab_telemetry_coursera/handlers.py
etc_jupyterlab_telemetry_coursera/labextension/build_log.json
etc_jupyterlab_telemetry_coursera/labextension/package.json
etc_jupyterlab_telemetry_coursera/labextension/schemas/@educational-technology-collective/etc_jupyterlab_telemetry_coursera/package.json.orig
etc_jupyterlab_telemetry_coursera/labextension/schemas/@educational-technology-collective/etc_jupyterlab_telemetry_coursera/plugin.json
etc_jupyterlab_telemetry_coursera/labextension/static/lib_index_js.956df5f7f862621b568d.js
etc_jupyterlab_telemetry_coursera/labextension/static/lib_index_js.956df5f7f862621b568d.js.map
etc_jupyterlab_telemetry_coursera/labextension/static/remoteEntry.bc589917776d3449ba28.js
etc_jupyterlab_telemetry_coursera/labextension/static/remoteEntry.bc589917776d3449ba28.js.map
etc_jupyterlab_telemetry_coursera/labextension/static/style.js
etc_jupyterlab_telemetry_coursera/labextension/static/style_index_js.c884da3e02a68333c1f4.js
etc_jupyterlab_telemetry_coursera/labextension/static/style_index_js.c884da3e02a68333c1f4.js.map
etc_jupyterlab_telemetry_coursera/labextension/static/vendors-node_modules_css-loader_dist_runtime_api_js-node_modules_css-loader_dist_runtime_cssW-72eba1.bde8c645bdfecdfc17b6.js
etc_jupyterlab_telemetry_coursera/labextension/static/vendors-node_modules_css-loader_dist_runtime_api_js-node_modules_css-loader_dist_runtime_cssW-72eba1.bde8c645bdfecdfc17b6.js.map
etc_jupyterlab_telemetry_coursera-5.0.2.data/data/etc/jupyter/jupyter_notebook_config.d/etc_jupyterlab_telemetry_coursera.json
etc_jupyterlab_telemetry_coursera-5.0.2.data/data/etc/jupyter/jupyter_server_config.d/etc_jupyterlab_telemetry_coursera.json
etc_jupyterlab_telemetry_coursera-5.0.2.data/data/share/jupyter/labextensions/@educational-technology-collective/etc_jupyterlab_telemetry_coursera/build_log.json
etc_jupyterlab_telemetry_coursera-5.0.2.dist-info/LICENSE
etc_jupyterlab_telemetry_coursera-5.0.2.dist-info/METADATA
etc_jupyterlab_telemetry_coursera-5.0.2.dist-info/WHEEL
etc_jupyterlab_telemetry_coursera-5.0.2.dist-info/top_level.txt
etc_jupyterlab_telemetry_coursera-5.0.2.dist-info/RECORD
