Metadata-Version: 2.1
Name: etc-jupyterlab-telemetry-coursera
Version: 5.0.2
Summary: A JupyterLab extension.
Home-page: https://github.com/educational-technology-collective/etc_jupyterlab_telemetry_coursera.git
Author: ETC
Author-email: 
License: BSD-3-Clause
Keywords: Jupyter,JupyterLab,JupyterLab3
Platform: Linux
Platform: Mac OS X
Platform: Windows
Classifier: License :: OSI Approved :: BSD License
Classifier: Programming Language :: Python
Classifier: Programming Language :: Python :: 3
Classifier: Programming Language :: Python :: 3.6
Classifier: Programming Language :: Python :: 3.7
Classifier: Programming Language :: Python :: 3.8
Classifier: Programming Language :: Python :: 3.9
Classifier: Framework :: Jupyter
Requires-Python: >=3.6
License-File: LICENSE
Requires-Dist: jupyter-server (<2,>=1.6)
Requires-Dist: etc-jupyterlab-notebook-state-provider (<3,>=2.0.0)
Requires-Dist: etc-jupyterlab-telemetry-library (<3,>=2.0.0)
Requires-Dist: etc-jupyterlab-feedback (<3,>=2.0.0)
Requires-Dist: requests (<3,>=2.0.0)
